templates/computation_analysis/Calculating_Average.py
templates/data_cleaning/DataFrame_Cleaning.py
templates/data_export/DataFrame_To_CSV.py
templates/data_loading/DataFrame_From_CSV.py
templates/data_transformation/Create_Buffer_GeoDataframe.py
templates/vega_lite/Barchart.py
tests/DataPool_UTK.json
tests/DataPool_Vega.json
tests/DataPool_Vega_2.json
tests/DataPool_df.json
tests/DataPool_gdf.json
tests/DefaultWorkflow.json
tests/Green_Roofs.csv
tests/Image.json
tests/Interaction.json
tests/Interaction_UTK.json
tests/Interaction_Vega.json
tests/Merge.json
tests/UTK.json
tests/Vega.json
tests/access_score_neighborhood.geojson
tests/chicago.geojson
tests/nyc_zip.geojson
tests/test.data
utk_curio/__init__.py
utk_curio/main.py
utk_curio/backend/.dockerignore
utk_curio/backend/.flaskenv
utk_curio/backend/.gitignore
utk_curio/backend/README.md
utk_curio/backend/__init__.py
utk_curio/backend/config.py
utk_curio/backend/create_provenance_db.py
utk_curio/backend/extensions.py
utk_curio/backend/pytest.ini
utk_curio/backend/server.py
utk_curio/backend/start_local.sh
utk_curio/backend/test.sh
utk_curio/backend/app/__init__.py
utk_curio/backend/app/middlewares.py
utk_curio/backend/app/api/__init__.py
utk_curio/backend/app/api/routes.py
utk_curio/backend/app/services/__init__.py
utk_curio/backend/app/services/google_oauth.py
utk_curio/backend/app/users/__init__.py
utk_curio/backend/app/users/models.py
utk_curio/backend/migrations/README
utk_curio/backend/migrations/alembic.ini
utk_curio/backend/migrations/env.py
utk_curio/backend/migrations/script.py.mako
utk_curio/backend/migrations/versions/13c00188213d_add_provider_and_provider_uid_to_user.py
utk_curio/backend/migrations/versions/62a73b08f79f_rename_profileimage_to_profile_image.py
utk_curio/backend/migrations/versions/8273cbb189e4_create_user.py
utk_curio/backend/migrations/versions/f5c32a160bb4_create_usersession_model.py
utk_curio/backend/tests/__init__.py
utk_curio/backend/tests/test_backend.py
utk_curio-0.5.8.1.dist-info/LICENSE
utk_curio-0.5.8.1.dist-info/METADATA
utk_curio-0.5.8.1.dist-info/WHEEL
utk_curio-0.5.8.1.dist-info/entry_points.txt
utk_curio-0.5.8.1.dist-info/top_level.txt
utk_curio-0.5.8.1.dist-info/RECORD
