Metadata-Version: 2.1
Name: utk-curio
Version: 0.5.8.1
Summary: Curio: A dataflow-based framework for urban visual analytics
Author-email: UTK <fabiom@uic.edu>
License: MIT License
Requires-Python: <3.12,>=3.10
License-File: LICENSE
Requires-Dist: requests==2.31.0
Requires-Dist: pyarrow==15.0.0
Requires-Dist: pillow==10.2.0
Requires-Dist: rasterio==1.3.9
Requires-Dist: python-dotenv==1.0.1
Requires-Dist: Flask==3.1.0
Requires-Dist: Flask-Caching==2.3.0
Requires-Dist: fiona==1.9.6
Requires-Dist: Flask-Migrate==4.0.5
Requires-Dist: Flask-SQLAlchemy==3.1.1
Requires-Dist: google-auth==2.27.0
Requires-Dist: pandas==2.2.1
Requires-Dist: geopandas==1.0.1
Requires-Dist: pytest==8.3.4
Requires-Dist: pytest-playwright==0.7.0
Requires-Dist: pytest-flask==1.3.0
Requires-Dist: black==24.10.0
